{"stats":{"minecraft:crafted":{"minecraft:oak_sign":18,"minecraft:diamond_shovel":3,"minecraft:cooked_mutton":22,"minecraft:shulker_box":5,"minecraft:quartz_block":65,"minecraft:glass":164,"minecraft:diamond_helmet":1,"minecraft:diamond_leggings":1,"minecraft:netherite_boots":1,"minecraft:birch_fence_gate":1,"minecraft:stone_pressure_plate":2,"minecraft:iron_door":9,"minecraft:birch_door":3,"minecraft:chiseled_quartz_block":10,"minecraft:magenta_dye":8,"minecraft:white_shulker_box":1,"minecraft:glass_bottle":3,"minecraft:wooden_shovel":1,"minecraft:emerald":3,"minecraft:cooked_porkchop":122,"minecraft:stone_brick_stairs":5067,"minecraft:wooden_hoe":4,"minecraft:stone_slab":6,"minecraft:iron_pickaxe":9,"minecraft:iron_block":6,"minecraft:gold_ingot":278,"minecraft:light_gray_dye":32,"minecraft:netherite_ingot":8,"minecraft:stone_shovel":1,"minecraft:pink_dye":25,"minecraft:quartz":140,"minecraft:diamond":15,"minecraft:polished_diorite":452,"minecraft:red_shulker_box":1,"minecraft:stone_pickaxe":6,"minecraft:diamond_boots":1,"minecraft:redstone_block":37,"minecraft:netherite_pickaxe":1,"minecraft:crimson_slab":30,"minecraft:glowstone":4,"minecraft:enchanted_book":19,"minecraft:orange_dye":33,"minecraft:oak_fence_gate":2,"minecraft:crimson_stairs":12,"minecraft:warped_fungus_on_a_stick":1,"minecraft:wooden_axe":6,"minecraft:iron_shovel":5,"minecraft:iron_leggings":2,"minecraft:white_bed":2,"minecraft:grindstone":2,"minecraft:oak_planks":838,"minecraft:cobblestone_slab":92,"minecraft:cooked_chicken":15,"minecraft:stone":390,"minecraft:hopper":2,"minecraft:bow":3,"minecraft:iron_boots":3,"minecraft:chest":28,"minecraft:netherite_helmet":1,"minecraft:oak_button":2,"minecraft:birch_button":1,"minecraft:oak_fence":45,"minecraft:quartz_stairs":3,"minecraft:oak_slab":12,"minecraft:item_frame":28,"minecraft:crafting_table":15,"minecraft:spruce_planks":128,"minecraft:wooden_pickaxe":6,"minecraft:baked_potato":1195,"minecraft:iron_helmet":3,"minecraft:chiseled_polished_blackstone":277,"minecraft:birch_planks":228,"minecraft:iron_chestplate":3,"minecraft:paper":105,"minecraft:diamond_pickaxe":5,"minecraft:yellow_dye":22,"minecraft:shield":10,"minecraft:stick":1032,"minecraft:iron_ingot":558,"minecraft:stone_sword":1,"minecraft:shears":2,"minecraft:wooden_sword":6,"minecraft:oak_door":6,"minecraft:fishing_rod":3,"minecraft:netherite_sword":1,"minecraft:furnace":21,"minecraft:stone_button":10,"minecraft:diamond_block":17,"minecraft:glass_pane":160,"minecraft:netherite_chestplate":1,"minecraft:netherite_leggings":1,"minecraft:yellow_shulker_box":1,"minecraft:iron_axe":4,"minecraft:iron_hoe":2,"minecraft:filled_map":1,"minecraft:netherite_scrap":34,"minecraft:cooked_beef":29,"minecraft:red_dye":117,"minecraft:cooked_cod":64,"minecraft:crimson_planks":236,"minecraft:diamond_sword":1,"minecraft:iron_trapdoor":1,"minecraft:iron_sword":4,"minecraft:bowl":8,"minecraft:bucket":2,"minecraft:stone_axe":1,"minecraft:bread":15,"minecraft:white_dye":28,"minecraft:stonecutter":1,"minecraft:crimson_door":6,"minecraft:anvil":2,"minecraft:torch":1622,"minecraft:lapis_lazuli":9,"minecraft:diamond_chestplate":1,"minecraft:firework_rocket":234},"minecraft:mined":{"minecraft:blackstone_stairs":2,"minecraft:red_shulker_box":4,"minecraft:white_bed":8,"minecraft:fire_coral_wall_fan":2,"minecraft:obsidian":32,"minecraft:carved_pumpkin":1,"minecraft:granite":1787,"minecraft:chiseled_polished_blackstone":1,"minecraft:bubble_coral_block":3,"minecraft:tube_coral_block":10,"minecraft:crimson_fungus":1,"minecraft:oak_wall_sign":11,"minecraft:oxeye_daisy":31,"minecraft:chiseled_stone_bricks":7,"minecraft:spawner":1,"minecraft:polished_blackstone_bricks":528,"minecraft:weeping_vines_plant":13,"minecraft:tall_seagrass":33,"minecraft:magma_block":163,"minecraft:fire":9,"minecraft:pumpkin":10,"minecraft:fletching_table":1,"minecraft:enchanting_table":3,"minecraft:oak_stairs":31,"minecraft:pink_tulip":25,"minecraft:white_shulker_box":11,"minecraft:brown_mushroom":5,"minecraft:kelp_plant":122,"minecraft:smoker":1,"minecraft:crimson_nylium":36,"minecraft:soul_fire":1,"minecraft:torch":48,"minecraft:melon":419,"minecraft:glass":3,"minecraft:tube_coral_fan":1,"minecraft:sugar_cane":52,"minecraft:spruce_sign":1,"minecraft:chain":7,"minecraft:wheat":2036,"minecraft:lilac":10,"minecraft:jukebox":1,"minecraft:pumpkin_stem":6,"minecraft:warped_fungus":7,"minecraft:stone_brick_stairs":7,"minecraft:grass":501,"minecraft:oak_fence_gate":3,"minecraft:birch_button":1,"minecraft:zombie_wall_head":1,"minecraft:red_mushroom_block":2,"minecraft:mossy_cobblestone":39,"minecraft:end_stone":3,"minecraft:shulker_box":33,"minecraft:nether_bricks":54,"minecraft:allium":20,"minecraft:crimson_roots":13,"minecraft:kelp":33,"minecraft:red_mushroom":1,"minecraft:horn_coral_wall_fan":1,"minecraft:horn_coral":1,"minecraft:redstone_ore":1070,"minecraft:snow":8,"minecraft:andesite":1502,"minecraft:potatoes":776,"minecraft:vine":2,"minecraft:rail":37,"minecraft:warped_stem":68,"minecraft:bone_block":29,"minecraft:fire_coral_block":3,"minecraft:oak_slab":16,"minecraft:glass_pane":60,"minecraft:soul_sand":244,"minecraft:lily_of_the_valley":32,"minecraft:dandelion":50,"minecraft:fire_coral":1,"minecraft:cornflower":4,"minecraft:emerald_ore":25,"minecraft:warped_roots":2,"minecraft:brain_coral_fan":1,"minecraft:tall_grass":117,"minecraft:diorite":1572,"minecraft:warped_wart_block":13,"minecraft:white_carpet":2,"minecraft:spruce_log":43,"minecraft:birch_leaves":145,"minecraft:gravel":1430,"minecraft:cobweb":20,"minecraft:oak_button":2,"minecraft:birch_sign":1,"minecraft:stone_bricks":2,"minecraft:gold_ore":179,"minecraft:iron_trapdoor":1,"minecraft:fern":5,"minecraft:infested_stone":24,"minecraft:spruce_planks":5,"minecraft:attached_melon_stem":3,"minecraft:brewing_stand":1,"minecraft:grass_block":1372,"minecraft:cracked_polished_blackstone_bricks":295,"minecraft:soul_soil":88,"minecraft:polished_diorite":52,"minecraft:polished_blackstone_brick_slab":1,"minecraft:composter":2,"minecraft:gilded_blackstone":5,"minecraft:glowstone":2,"minecraft:iron_ore":732,"minecraft:anvil":1,"minecraft:azure_bluet":73,"minecraft:red_tulip":55,"minecraft:iron_bars":1,"minecraft:birch_wall_sign":1,"minecraft:brain_coral_block":10,"minecraft:quartz_block":13,"minecraft:blackstone":1137,"minecraft:twisting_vines_plant":1,"minecraft:chiseled_quartz_block":3,"minecraft:clay":18,"minecraft:poppy":130,"minecraft:chest":14,"minecraft:nether_quartz_ore":932,"minecraft:cobblestone":576,"minecraft:prismarine":3,"minecraft:grindstone":2,"minecraft:oak_planks":134,"minecraft:iron_door":3,"minecraft:wall_torch":74,"minecraft:seagrass":17,"minecraft:warped_nylium":42,"minecraft:nether_wart_block":14,"minecraft:birch_log":106,"minecraft:orange_tulip":41,"minecraft:oak_log":522,"minecraft:beetroots":189,"minecraft:sand":1183,"minecraft:dirt":2762,"minecraft:ancient_debris":15,"minecraft:netherrack":40713,"minecraft:oak_leaves":850,"minecraft:horn_coral_block":13,"minecraft:nether_gold_ore":294,"minecraft:tube_coral":1,"minecraft:diamond_ore":144,"minecraft:crying_obsidian":13,"minecraft:quartz_stairs":1,"minecraft:oak_door":3,"minecraft:ladder":2,"minecraft:tube_coral_wall_fan":3,"minecraft:stone_button":2,"minecraft:weeping_vines":1,"minecraft:spruce_leaves":121,"minecraft:sandstone":96,"minecraft:crimson_stem":187,"minecraft:large_fern":17,"minecraft:furnace":7,"minecraft:carrots":138,"minecraft:polished_basalt":18,"minecraft:nether_sprouts":1,"minecraft:peony":16,"minecraft:gold_block":25,"minecraft:bell":2,"minecraft:nether_brick_fence":2,"minecraft:bookshelf":109,"minecraft:shroomlight":21,"minecraft:lantern":10,"minecraft:packed_ice":99,"minecraft:white_tulip":24,"minecraft:stone":26079,"minecraft:yellow_shulker_box":42,"minecraft:magenta_stained_glass":1,"minecraft:basalt":506,"minecraft:oak_fence":21,"minecraft:crafting_table":21,"minecraft:rose_bush":18,"minecraft:quartz_bricks":2,"minecraft:lapis_ore":131,"minecraft:lily_pad":67,"minecraft:polished_blackstone_brick_stairs":7,"minecraft:birch_planks":147,"minecraft:bubble_coral":2,"minecraft:sea_pickle":23,"minecraft:sweet_berry_bush":47,"minecraft:ice":6,"minecraft:yellow_bed":13,"minecraft:grass_path":17,"minecraft:coal_ore":2449,"minecraft:cocoa":4,"minecraft:bubble_coral_wall_fan":2,"minecraft:cracked_stone_bricks":1,"minecraft:mossy_stone_bricks":2},"minecraft:used":{"minecraft:beetroot":61,"minecraft:ladder":17,"minecraft:chest":34,"minecraft:stone":160,"minecraft:white_shulker_box":11,"minecraft:quartz_stairs":4,"minecraft:rotten_flesh":32,"minecraft:soul_sand":122,"minecraft:packed_ice":32,"minecraft:lava_bucket":1,"minecraft:quartz_block":60,"minecraft:stone_brick_stairs":227,"minecraft:bow":1642,"minecraft:sweet_berries":333,"minecraft:furnace":30,"minecraft:cooked_cod":29,"minecraft:egg":40,"minecraft:potato":1155,"minecraft:diorite":4,"minecraft:warped_fungus_on_a_stick":2,"minecraft:blackstone":275,"minecraft:wooden_pickaxe":62,"minecraft:composter":2,"minecraft:oak_leaves":359,"minecraft:golden_apple":2,"minecraft:sand":20,"minecraft:blast_furnace":2,"minecraft:chiseled_quartz_block":7,"minecraft:pumpkin_seeds":8,"minecraft:birch_fence":1,"minecraft:crying_obsidian":9,"minecraft:zombie_head":1,"minecraft:stone_button":8,"minecraft:diamond_sword":3489,"minecraft:wooden_sword":153,"minecraft:enchanting_table":3,"minecraft:stone_sword":11,"minecraft:carved_pumpkin":1,"minecraft:cooked_salmon":52,"minecraft:netherrack":394,"minecraft:torch":1578,"minecraft:anvil":3,"minecraft:dead_brain_coral_block":1,"minecraft:oak_fence_gate":4,"minecraft:polished_diorite":569,"minecraft:shroomlight":7,"minecraft:red_shulker_box":4,"minecraft:iron_axe":2143,"minecraft:melon_seeds":26,"minecraft:basalt":51,"minecraft:glowstone":25,"minecraft:beef":1,"minecraft:iron_trapdoor":1,"minecraft:crimson_stem":49,"minecraft:wheat_seeds":2220,"minecraft:water_bucket":240,"minecraft:birch_planks":4,"minecraft:lead":3,"minecraft:yellow_shulker_box":42,"minecraft:polished_blackstone_bricks":77,"minecraft:oak_slab":12,"minecraft:crafting_table":32,"minecraft:white_bed":7,"minecraft:oak_log":86,"minecraft:diamond_pickaxe":16577,"minecraft:diamond_shovel":5212,"minecraft:oak_button":2,"minecraft:iron_pickaxe":1965,"minecraft:cobblestone":1527,"minecraft:porkchop":4,"minecraft:cooked_porkchop":106,"minecraft:glass_pane":194,"minecraft:kelp":112,"minecraft:jukebox":2,"minecraft:iron_shovel":1217,"minecraft:bone_block":2,"minecraft:oak_sign":23,"minecraft:shield":463,"minecraft:iron_sword":1156,"minecraft:bell":2,"minecraft:debug_stick":5,"minecraft:mutton":13,"minecraft:nether_bricks":5,"minecraft:carrot":392,"minecraft:music_disc_13":2,"minecraft:obsidian":19,"minecraft:glass":49,"minecraft:lantern":7,"minecraft:item_frame":28,"minecraft:birch_button":1,"minecraft:magma_block":6,"minecraft:beetroot_seeds":189,"minecraft:skeleton_skull":1,"minecraft:chiseled_polished_blackstone":26,"minecraft:birch_leaves":40,"minecraft:stone_pickaxe":706,"minecraft:oak_planks":25,"minecraft:mushroom_stew":2,"minecraft:crossbow":4,"minecraft:shears":469,"minecraft:firework_rocket":3,"minecraft:birch_fence_gate":1,"minecraft:melon_slice":95,"minecraft:bread":61,"minecraft:iron_door":10,"minecraft:gravel":38,"minecraft:grindstone":4,"minecraft:crimson_door":4,"minecraft:andesite":21,"minecraft:experience_bottle":336,"minecraft:trident":3204,"minecraft:oak_fence":75,"minecraft:netherite_sword":6069,"minecraft:flint_and_steel":11,"minecraft:tropical_fish":2,"minecraft:stone_shovel":133,"minecraft:cooked_chicken":49,"minecraft:oak_door":8,"minecraft:dirt":1007,"minecraft:hopper":2,"minecraft:shulker_box":35,"minecraft:granite":89,"minecraft:birch_door":3,"minecraft:iron_hoe":1484,"minecraft:wooden_axe":98,"minecraft:bookshelf":115,"minecraft:oak_stairs":4,"minecraft:crimson_slab":15,"minecraft:crimson_planks":125,"minecraft:golden_carrot":4,"minecraft:soul_soil":1,"minecraft:netherite_pickaxe":62996,"minecraft:stone_pressure_plate":2,"minecraft:cooked_beef":36,"minecraft:pumpkin":3,"minecraft:quartz_bricks":6,"minecraft:cooked_mutton":26,"minecraft:iron_ore":3,"minecraft:baked_potato":1005,"minecraft:stonecutter":1,"minecraft:cobblestone_slab":17,"minecraft:music_disc_cat":4,"minecraft:smoker":4,"minecraft:wooden_hoe":343,"minecraft:cracked_polished_blackstone_bricks":1,"minecraft:chicken":6,"minecraft:stone_axe":2,"minecraft:fishing_rod":349,"minecraft:white_banner":3,"minecraft:bucket":245,"minecraft:yellow_bed":13,"minecraft:gray_wool":2},"minecraft:picked_up":{"minecraft:wooden_axe":4,"minecraft:iron_chestplate":13,"minecraft:anvil":1,"minecraft:chainmail_boots":4,"minecraft:creeper_head":1,"minecraft:prismarine_shard":20,"minecraft:stone_slab":9,"minecraft:lead":52,"minecraft:diamond_sword":8,"minecraft:oak_stairs":102,"minecraft:enchanted_book":9,"minecraft:birch_button":1,"minecraft:brewing_stand":1,"minecraft:golden_sword":3,"minecraft:music_disc_cat":4,"minecraft:string":568,"minecraft:soul_soil":32,"minecraft:cooked_salmon":64,"minecraft:pufferfish":32,"minecraft:shroomlight":20,"minecraft:beetroot":196,"minecraft:diamond_leggings":1,"minecraft:gold_nugget":1024,"minecraft:spruce_planks":124,"minecraft:coal_block":28,"minecraft:melon_slice":2729,"minecraft:diamond_ore":5,"minecraft:golden_helmet":12,"minecraft:jukebox":2,"minecraft:composter":2,"minecraft:purpur_pillar":3,"minecraft:golden_chestplate":13,"minecraft:tropical_fish":11,"minecraft:polished_basalt":16,"minecraft:red_tulip":32,"minecraft:carved_pumpkin":1,"minecraft:glowstone":8,"minecraft:bookshelf":108,"minecraft:netherite_chestplate":3,"minecraft:blaze_rod":3,"minecraft:iron_bars":4,"minecraft:birch_log":128,"minecraft:magma_block":175,"minecraft:feather":101,"minecraft:cooked_beef":25,"minecraft:iron_door":3,"minecraft:water_bucket":7,"minecraft:brown_wool":2,"minecraft:smoker":4,"minecraft:flint":294,"minecraft:netherite_leggings":1,"minecraft:lantern":13,"minecraft:diamond_helmet":2,"minecraft:glowstone_dust":89,"minecraft:warped_wart_block":14,"minecraft:ink_sac":12,"minecraft:dark_oak_log":2,"minecraft:iron_hoe":3,"minecraft:quartz_bricks":2,"minecraft:polished_andesite":36,"minecraft:dead_brain_coral_block":5,"minecraft:granite":1220,"minecraft:bread":57,"minecraft:chainmail_helmet":2,"minecraft:crimson_roots":12,"minecraft:diamond_pickaxe":6,"minecraft:crafting_table":24,"minecraft:clay_ball":24,"minecraft:leather_leggings":17,"minecraft:purpur_block":1,"minecraft:dead_horn_coral_block":15,"minecraft:cornflower":1,"minecraft:red_bed":2,"minecraft:elytra":6,"minecraft:flint_and_steel":1,"minecraft:netherite_scrap":1,"minecraft:white_carpet":15,"minecraft:iron_shovel":6,"minecraft:glass_pane":86,"minecraft:netherite_sword":10,"minecraft:beef":101,"minecraft:iron_nugget":19,"minecraft:poppy":123,"minecraft:quartz_stairs":2,"minecraft:chest":13,"minecraft:birch_sapling":22,"minecraft:egg":60,"minecraft:sandstone":42,"minecraft:stone":1336,"minecraft:oak_door":19,"minecraft:fire_charge":1,"minecraft:white_dye":27,"minecraft:carrot":898,"minecraft:cyan_shulker_box":1,"minecraft:redstone":2368,"minecraft:netherite_pickaxe":7,"minecraft:prismarine_crystals":7,"minecraft:diamond_chestplate":2,"minecraft:beetroot_seeds":504,"minecraft:peony":19,"minecraft:shears":1,"minecraft:diamond_boots":1,"minecraft:gold_ingot":71,"minecraft:totem_of_undying":3,"minecraft:white_shulker_box":11,"minecraft:mutton":70,"minecraft:bone_block":29,"minecraft:white_wool":49,"minecraft:rail":41,"minecraft:emerald_ore":2,"minecraft:oxeye_daisy":47,"minecraft:lapis_ore":8,"minecraft:birch_leaves":45,"minecraft:yellow_shulker_box":43,"minecraft:red_mushroom":1,"minecraft:oak_log":839,"minecraft:lily_pad":64,"minecraft:ancient_debris":47,"minecraft:golden_boots":14,"minecraft:paper":19,"minecraft:white_banner":12,"minecraft:apple":15,"minecraft:kelp":379,"minecraft:warped_stem":64,"minecraft:stone_pickaxe":2,"minecraft:oak_fence_gate":3,"minecraft:iron_ore":901,"minecraft:iron_sword":15,"minecraft:sweet_berries":2313,"minecraft:gravel":457,"minecraft:birch_stairs":21,"minecraft:dead_fire_coral_block":2,"minecraft:crimson_stairs":49,"minecraft:spruce_sapling":13,"minecraft:spruce_log":107,"minecraft:crying_obsidian":15,"minecraft:leather_helmet":10,"minecraft:firework_rocket":102,"minecraft:diamond_shovel":3,"minecraft:coal_ore":3,"minecraft:polished_diorite":441,"minecraft:redstone_ore":63,"minecraft:birch_sign":4,"minecraft:gray_wool":7,"minecraft:warped_roots":2,"minecraft:oak_button":2,"minecraft:baked_potato":130,"minecraft:melon_seeds":20,"minecraft:warped_nylium":1,"minecraft:ender_pearl":64,"minecraft:shulker_shell":4,"minecraft:wheat":2154,"minecraft:nether_brick_fence":2,"minecraft:redstone_block":78,"minecraft:iron_trapdoor":1,"minecraft:stone_brick_stairs":106,"minecraft:crimson_planks":10,"minecraft:dead_tube_coral_block":16,"minecraft:iron_leggings":9,"minecraft:netherite_ingot":7,"minecraft:zombie_head":2,"minecraft:oak_sign":7,"minecraft:sea_pickle":42,"minecraft:bucket":6,"minecraft:white_tulip":24,"minecraft:rose_bush":19,"minecraft:cobblestone_slab":13,"minecraft:wooden_shovel":7,"minecraft:iron_pickaxe":3,"minecraft:iron_boots":9,"minecraft:furnace":10,"minecraft:tipped_arrow":1,"minecraft:stick":187,"minecraft:oak_fence":30,"minecraft:torch":312,"minecraft:porkchop":193,"minecraft:netherite_shovel":1,"minecraft:diorite":1050,"minecraft:quartz_block":13,"minecraft:nether_gold_ore":57,"minecraft:rotten_flesh":2483,"minecraft:obsidian":45,"minecraft:cod":148,"minecraft:cobblestone":11585,"minecraft:nautilus_shell":6,"minecraft:enchanting_table":3,"minecraft:leather_chestplate":17,"minecraft:lilac":10,"minecraft:magma_cream":10,"minecraft:andesite":740,"minecraft:golden_leggings":15,"minecraft:chiseled_quartz_block":3,"minecraft:potato":3062,"minecraft:dirt":2993,"minecraft:lapis_lazuli":1213,"minecraft:leather_boots":11,"minecraft:glass":37,"minecraft:bone":850,"minecraft:bow":79,"minecraft:wheat_seeds":5352,"minecraft:orange_tulip":39,"minecraft:bell":2,"minecraft:grindstone":2,"minecraft:netherite_axe":1,"minecraft:mossy_stone_bricks":1,"minecraft:fletching_table":1,"minecraft:bamboo":84,"minecraft:prismarine":3,"minecraft:oak_planks":247,"minecraft:cooked_porkchop":9,"minecraft:music_disc_13":3,"minecraft:oak_pressure_plate":2,"minecraft:poisonous_potato":36,"minecraft:sand":774,"minecraft:jungle_planks":2,"minecraft:grass_block":10,"minecraft:lily_of_the_valley":29,"minecraft:spectral_arrow":12,"minecraft:shulker_box":37,"minecraft:sugar":3,"minecraft:diamond":386,"minecraft:netherite_helmet":3,"minecraft:cracked_polished_blackstone_bricks":159,"minecraft:crossbow":7,"minecraft:bone_meal":92,"minecraft:spruce_sign":1,"minecraft:emerald":71,"minecraft:oak_sapling":79,"minecraft:netherrack":10612,"minecraft:oak_leaves":360,"minecraft:azure_bluet":42,"minecraft:cocoa_beans":36,"minecraft:fishing_rod":5,"minecraft:allium":22,"minecraft:chicken":69,"minecraft:ladder":18,"minecraft:packed_ice":96,"minecraft:brown_mushroom":11,"minecraft:wooden_pickaxe":6,"minecraft:gold_block":25,"minecraft:chain":6,"minecraft:shield":4,"minecraft:iron_axe":7,"minecraft:wooden_sword":4,"minecraft:blackstone":904,"minecraft:player_head":4,"minecraft:light_gray_wool":8,"minecraft:sugar_cane":209,"minecraft:phantom_membrane":97,"minecraft:bowl":5,"minecraft:polished_blackstone_bricks":290,"minecraft:trident":17,"minecraft:arrow":1122,"minecraft:weeping_vines":10,"minecraft:red_shulker_box":4,"minecraft:nether_bricks":64,"minecraft:pink_tulip":25,"minecraft:saddle":5,"minecraft:skeleton_skull":1,"minecraft:wet_sponge":1,"minecraft:netherite_boots":1,"minecraft:jungle_boat":1,"minecraft:basalt":279,"minecraft:golden_carrot":42,"minecraft:crimson_stem":272,"minecraft:salmon":126,"minecraft:leather":120,"minecraft:birch_planks":176,"minecraft:mushroom_stew":2,"minecraft:crimson_fungus":2,"minecraft:chainmail_chestplate":2,"minecraft:yellow_bed":13,"minecraft:gunpowder":602,"minecraft:wooden_hoe":2,"minecraft:cooked_mutton":20,"minecraft:iron_ingot":345,"minecraft:cooked_chicken":40,"minecraft:soul_sand":181,"minecraft:book":84,"minecraft:oak_slab":14,"minecraft:warped_fungus":7,"minecraft:nether_quartz_ore":132,"minecraft:pumpkin":18,"minecraft:chiseled_stone_bricks":1,"minecraft:quartz":808,"minecraft:dandelion":66,"minecraft:blast_furnace":4,"minecraft:white_bed":9,"minecraft:gold_ore":226,"minecraft:spider_eye":92,"minecraft:pumpkin_seeds":44,"minecraft:dead_bubble_coral_block":2,"minecraft:chainmail_leggings":4,"minecraft:iron_helmet":8,"minecraft:black_wool":2,"minecraft:coal":2600},"minecraft:killed":{"minecraft:cave_spider":8,"minecraft:cod":3,"minecraft:shulker":8,"minecraft:skeleton":2042,"minecraft:guardian":41,"minecraft:chicken":78,"minecraft:magma_cube":182,"minecraft:elder_guardian":1,"minecraft:salmon":29,"minecraft:ender_dragon":1,"minecraft:pillager":80,"minecraft:donkey":2,"minecraft:zombie":2752,"minecraft:cow":37,"minecraft:evoker":3,"minecraft:vindicator":16,"minecraft:horse":5,"minecraft:husk":1,"minecraft:ravager":3,"minecraft:polar_bear":1,"minecraft:enderman":63,"minecraft:zombified_piglin":9,"minecraft:witch":27,"minecraft:spider":321,"minecraft:silverfish":27,"minecraft:piglin_brute":9,"minecraft:wolf":2,"minecraft:piglin":67,"minecraft:pig":74,"minecraft:zombie_villager":48,"minecraft:creeper":1553,"minecraft:sheep":68,"minecraft:ghast":8,"minecraft:mooshroom":10,"minecraft:stray":3,"minecraft:blaze":15,"minecraft:vex":4,"minecraft:phantom":258,"minecraft:drowned":1250,"minecraft:hoglin":40,"minecraft:squid":13,"minecraft:wither_skeleton":2},"minecraft:killed_by":{"minecraft:piglin_brute":5,"minecraft:vindicator":1,"minecraft:zombie":14,"minecraft:creeper":8,"minecraft:piglin":5,"minecraft:elder_guardian":1,"minecraft:player":2,"minecraft:spider":2,"minecraft:enderman":7,"minecraft:skeleton":4},"minecraft:broken":{"minecraft:shears":2,"minecraft:iron_sword":1,"minecraft:leather_helmet":1,"minecraft:shield":7,"minecraft:iron_axe":4,"minecraft:iron_pickaxe":7,"minecraft:wooden_hoe":3,"minecraft:iron_shovel":3,"minecraft:golden_leggings":1,"minecraft:stone_pickaxe":5},"minecraft:custom":{"minecraft:interact_with_crafting_table":605,"minecraft:bell_ring":180,"minecraft:leave_game":85,"minecraft:time_since_death":138781,"minecraft:damage_blocked_by_shield":26131,"minecraft:deaths":59,"minecraft:jump":90315,"minecraft:enchant_item":61,"minecraft:interact_with_furnace":345,"minecraft:play_record":6,"minecraft:traded_with_villager":19,"minecraft:sleep_in_bed":76,"minecraft:damage_dealt":776712,"minecraft:interact_with_smoker":145,"minecraft:horse_one_cm":12454373,"minecraft:interact_with_smithing_table":35,"minecraft:interact_with_anvil":102,"minecraft:inspect_hopper":14,"minecraft:damage_dealt_absorbed":95,"minecraft:sneak_time":158793,"minecraft:interact_with_lectern":4,"minecraft:interact_with_blast_furnace":107,"minecraft:tune_noteblock":39,"minecraft:interact_with_stonecutter":47,"minecraft:time_since_rest":2494,"minecraft:swim_one_cm":5153673,"minecraft:fly_one_cm":18290362,"minecraft:open_chest":4221,"minecraft:fish_caught":271,"minecraft:fall_one_cm":1867855,"minecraft:animals_bred":50,"minecraft:open_shulker_box":212,"minecraft:sprint_one_cm":22558238,"minecraft:drop":1890,"minecraft:talked_to_villager":73,"minecraft:interact_with_brewingstand":2,"minecraft:walk_on_water_one_cm":2101116,"minecraft:play_one_minute":9392442,"minecraft:open_enderchest":366,"minecraft:interact_with_beacon":1,"minecraft:player_kills":21,"minecraft:crouch_one_cm":738717,"minecraft:mob_kills":9210,"minecraft:climb_one_cm":87832,"minecraft:walk_one_cm":25032187,"minecraft:raid_win":2,"minecraft:strider_one_cm":4015772,"minecraft:walk_under_water_one_cm":5935312,"minecraft:raid_trigger":2,"minecraft:pot_flower":1,"minecraft:interact_with_grindstone":24,"minecraft:damage_taken":60529,"minecraft:damage_absorbed":45,"minecraft:aviate_one_cm":26974485},"minecraft:dropped":{"minecraft:crimson_stem":40,"minecraft:iron_sword":13,"minecraft:lapis_lazuli":131,"minecraft:glass_bottle":1,"minecraft:diamond":182,"minecraft:crafting_table":2,"minecraft:cooked_porkchop":13,"minecraft:orange_tulip":6,"minecraft:weeping_vines":10,"minecraft:warped_roots":2,"minecraft:saddle":1,"minecraft:elytra":1,"minecraft:leather_helmet":6,"minecraft:rail":4,"minecraft:red_mushroom":1,"minecraft:emerald":15,"minecraft:dirt":1179,"minecraft:red_bed":3,"minecraft:stone_button":2,"minecraft:gold_nugget":13,"minecraft:wooden_sword":5,"minecraft:sand":460,"minecraft:sunflower":1,"minecraft:phantom_membrane":23,"minecraft:iron_pickaxe":2,"minecraft:fishing_rod":3,"minecraft:white_wool":6,"minecraft:bone":368,"minecraft:oak_door":7,"minecraft:ancient_debris":3,"minecraft:sugar_cane":3,"minecraft:iron_nugget":34,"minecraft:golden_chestplate":5,"minecraft:wheat":82,"minecraft:netherite_sword":8,"minecraft:birch_sapling":11,"minecraft:rotten_flesh":855,"minecraft:oak_planks":75,"minecraft:netherite_shovel":1,"minecraft:glowstone_dust":41,"minecraft:azure_bluet":30,"minecraft:white_bed":2,"minecraft:dead_fire_coral_block":2,"minecraft:salmon":64,"minecraft:coal_ore":3,"minecraft:leather_boots":8,"minecraft:leather_leggings":16,"minecraft:white_dye":27,"minecraft:glass":34,"minecraft:beef":5,"minecraft:warped_wart_block":3,"minecraft:egg":4,"minecraft:dead_tube_coral_block":16,"minecraft:enchanted_book":1,"minecraft:golden_boots":7,"minecraft:iron_ingot":477,"minecraft:netherite_pickaxe":6,"minecraft:birch_leaves":5,"minecraft:wheat_seeds":378,"minecraft:netherite_helmet":2,"minecraft:feather":31,"minecraft:oak_fence":3,"minecraft:book":3,"minecraft:iron_helmet":6,"minecraft:cobblestone":8621,"minecraft:granite":898,"minecraft:chainmail_helmet":2,"minecraft:coal":319,"minecraft:polished_andesite":72,"minecraft:pufferfish":3,"minecraft:oxeye_daisy":12,"minecraft:crimson_stairs":16,"minecraft:gray_wool":4,"minecraft:golden_carrot":15,"minecraft:ink_sac":6,"minecraft:wooden_hoe":2,"minecraft:wooden_axe":4,"minecraft:rose_bush":9,"minecraft:cooked_salmon":16,"minecraft:diamond_helmet":1,"minecraft:oak_stairs":10,"minecraft:white_banner":6,"minecraft:iron_shovel":3,"minecraft:chainmail_leggings":2,"minecraft:paper":42,"minecraft:string":300,"minecraft:spruce_sapling":12,"minecraft:purpur_pillar":3,"minecraft:soul_soil":3,"minecraft:player_head":1,"minecraft:netherite_ingot":4,"minecraft:cocoa_beans":36,"minecraft:bowl":6,"minecraft:chicken":2,"minecraft:iron_boots":6,"minecraft:stone_slab":11,"minecraft:oak_sign":15,"minecraft:pumpkin_seeds":4,"minecraft:diamond_sword":7,"minecraft:potato":18,"minecraft:cobblestone_slab":12,"minecraft:stone":640,"minecraft:allium":22,"minecraft:peony":6,"minecraft:spruce_planks":136,"minecraft:diamond_pickaxe":5,"minecraft:wooden_shovel":6,"minecraft:spider_eye":46,"minecraft:bamboo":64,"minecraft:sandstone":42,"minecraft:bow":62,"minecraft:magma_block":140,"minecraft:gold_ore":6,"minecraft:brown_mushroom":16,"minecraft:birch_planks":198,"minecraft:oak_log":80,"minecraft:baked_potato":257,"minecraft:ender_pearl":1,"minecraft:leather":14,"minecraft:jungle_planks":1,"minecraft:cod":5,"minecraft:flint":35,"minecraft:cracked_polished_blackstone_bricks":2,"minecraft:cornflower":3,"minecraft:mutton":9,"minecraft:polished_blackstone_bricks":9,"minecraft:birch_log":19,"minecraft:gold_ingot":2,"minecraft:gravel":274,"minecraft:white_tulip":3,"minecraft:chiseled_polished_blackstone":2,"minecraft:purpur_block":1,"minecraft:blackstone":145,"minecraft:diamond_shovel":5,"minecraft:cyan_shulker_box":1,"minecraft:cooked_mutton":3,"minecraft:carrot":70,"minecraft:chainmail_chestplate":2,"minecraft:chiseled_stone_bricks":1,"minecraft:poppy":42,"minecraft:oak_fence_gate":1,"minecraft:leather_chestplate":14,"minecraft:trident":14,"minecraft:gunpowder":196,"minecraft:beetroot_seeds":1,"minecraft:melon_seeds":6,"minecraft:glowstone":2,"minecraft:chainmail_boots":2,"minecraft:birch_button":1,"minecraft:iron_ore":225,"minecraft:basalt":14,"minecraft:arrow":81,"minecraft:oak_leaves":22,"minecraft:netherrack":6112,"minecraft:firework_rocket":25,"minecraft:bread":3,"minecraft:water_bucket":7,"minecraft:golden_helmet":6,"minecraft:lilac":6,"minecraft:diamond_leggings":2,"minecraft:poisonous_potato":34,"minecraft:netherite_axe":1,"minecraft:lead":1,"minecraft:dead_horn_coral_block":15,"minecraft:tropical_fish":1,"minecraft:grass_block":9,"minecraft:stick":130,"minecraft:diorite":737,"minecraft:torch":79,"minecraft:melon_slice":192,"minecraft:fire_charge":1,"minecraft:iron_leggings":7,"minecraft:iron_axe":3,"minecraft:polished_basalt":1,"minecraft:bucket":1,"minecraft:dandelion":20,"minecraft:redstone":828,"minecraft:polished_diorite":257,"minecraft:sweet_berries":41,"minecraft:kelp":135,"minecraft:dead_bubble_coral_block":1,"minecraft:light_gray_wool":4,"minecraft:iron_hoe":2,"minecraft:shulker_box":2,"minecraft:glass_pane":40,"minecraft:shield":1,"minecraft:oak_button":1,"minecraft:diamond_chestplate":2,"minecraft:iron_chestplate":9,"minecraft:andesite":434,"minecraft:golden_leggings":6,"minecraft:oak_sapling":70,"minecraft:golden_sword":1,"minecraft:spruce_log":11,"minecraft:birch_sign":2,"minecraft:diamond_boots":1,"minecraft:stone_pickaxe":1,"minecraft:dead_brain_coral_block":4,"minecraft:wooden_pickaxe":6,"minecraft:nether_quartz_ore":5,"minecraft:nautilus_shell":3}},"DataVersion":2584}